{
    "name": "smarttext",
    "version": "0.1.0",
    "title": "smarttext",
    "author": {
        "name": "Joe Wagner",
        "url": "https://github.com/joewagner"
    },
    "licenses": [
        {
            "type": "MIT",
            "url": "https://raw.githubusercontent.com/JoeWagner/smarttext/master/LICENSE"
        }
    ],
    "dependencies": {
        "jquery": "~1.10.2"
    },
    "homepage": "https://github.com/JoeWagner/smarttext",
    "keywords": [
        "content",
        "contenteditable",
        "escape",
        "escaping",
        "html5"
    ],
    "description": "JQuery plugin to enhance contenteditable attribute",
    "bugs": "https://github.com/JoeWagner/smarttext/issues"
}